{
  "主题": "美国耶稣基督末世圣徒教会投资基金Ensign Peak Advisors二季度持仓报告",
  "元信息": {
    "关键词": "美国耶稣基督末世圣徒教会 EnsignPeakAdvisors 二季度 持仓报告 股票投资组合 投资基金"
  },
  "详情": {
    "时间": "08-15 10:21",
    "地点": "美国",
    "组织机构": "美国耶稣基督末世圣徒教会（摩门教）",
    "机构/单位和完整头衔": "EnsignPeakAdvisors",
    "人物观点": {
      "姓名(机构/单位和完整头衔)": "EnsignPeakAdvisors",
      "观点原话": "其股票投资组合的规模达到493亿美元，较第一季度末增加了31亿美元。"
    },
    "人物观点2": {
      "姓名(机构/单位和完整头衔)": "美国证券交易委员会（SEC）",
      "观点原话": "由于多年来缺乏披露，该基金今年2月被罚款500万美元，以了结有关其试图通过空壳公司隐瞒投资组合的指控。"
    },
    "人物观点3": {
      "姓名(机构/单位和完整头衔)": "该基金的一名前雇员",
      "观点原话": "该基金每季度公布持仓报告。"
    },
    "人物观点4": {
      "姓名(机构/单位和完整头衔)": "该基金的一名前雇员",
      "观点原话": "称该基金不应享有免税地位，因为其不参与任何慈善活动。"
    },
    "人物观点5": {
      "姓名(机构/单位和完整头衔)": "该基金的一名前雇员",
      "观点原话": "自2019年以来，该基金每季度公布持仓报告。"
    },
    "股票投资组合": [
      {
        "股票名称": "苹果",
        "股票代码": "AAPL",
        "变动方向": "增持",
        "变动数量": "259436股",
        "持仓总额": "31.2亿美元"
      },
      {
        "股票名称": "微软",
        "股票代码": "MSFT",
        "变动方向": "增持",
        "变动数量": "250586股",
        "持仓总额": "22.3亿美元"
      },
      {
        "股票名称": "谷歌",
        "股票代码": "GOOGL",
        "变动方向": "减持",
        "变动数量": "209983股",
        "持仓总额": "16.2亿美元"
      },
      {
        "股票名称": "亚马逊",
        "股票代码": "AMZN",
        "变动方向": "增持",
        "变动数量": "217652股",
        "持仓总额": "12.5亿美元"
      },
      {
        "股票名称": "英伟达",
        "股票代码": "NVDA",
        "变动方向": "增持",
        "变动数量": "227659股",
        "持仓总额": "12亿美元"
      },
      {
        "股票名称": "联合健康",
        "股票代码": "UNH",
        "变动方向": "减持",
        "变动数量": "70529股",
        "持仓总额": "9.83亿美元"
      },
      {
        "股票名称": "MetaPlatforms",
        "股票代码": "META",
        "变动方向": "增持",
        "变动数量": "224849股",
        "持仓总额": "9.708亿美元"
      },
      {
        "股票名称": "万事达卡",
        "股票代码": "MA",
        "变动方向": "增持",
        "变动数量": "37013股",
        "持仓总额": "7.838亿美元"
      },
      {
        "股票名称": "埃克森美孚",
        "股票代码": "XOM",
        "变动方向": "减持",
        "变动数量": "312853股",
        "持仓总额": "7.566亿美元"
      },
      {
        "股票名称": "摩根大通",
        "股票代码": "JPM",
        "变动方向": "减持",
        "变动数量": "171905股",
        "持仓总额": "6.661亿美元"
      }
    ]
  }
}