{
    "主题": "菜粕市场价格走势",
    "元信息": {
        "关键词": "菜粕 价格 上涨 豆粕"
    },
    "详情": {
        "菜粕价格走势": {
            "价格上涨原因": "豆粕表现强势，菜粕跟随其走势；菜粕供应不宽松，叠加下游有刚需",
            "具体走势": "自7月中旬菜粕价格上冲至4100元/吨的高位后，市场迎来了一波回调，至7月底国内36%蛋白菜粕现货价格调整至3860元/吨，跌幅5.85%。进入8月后菜粕价格稳步上涨，至8月15日收盘，国内36%蛋白菜粕现货报价至4120元/吨，打破前期4100元/吨的高位。与前期不同的是，此次豆菜粕价差大于前期。",
            "价格对比": "7月中旬菜粕价格冲高后，豆菜粕价差压缩至300元/吨之内，菜粕市场实际交易一度僵持，饲料厂更改配方的意愿增强，需求受损后菜粕价格转而下跌。此次菜粕价格虽在高位但豆菜粕价差保持在500元/吨之上，菜粕有一定的性价比优势，实际交易稍好。",
            "相关因素": {
                "豆粕价格上涨": "带动菜粕市场",
                "菜籽压榨企业开工维持低位": "菜粕供应有限",
                "水产养殖旺季": "下游对于菜粕有一定刚需"
            }
        },
        "豆粕市场需求": {
            "弱化迹象": "建议关注市场波动变化的影响"
        }
    }
}