{
    "主题": "天津市人民政府与中国大唐集团有限公司签署战略合作协议",
    "元信息":{
        "关键词": "天津市人民政府 中国大唐集团 战略合作协议 签署"
},
    "详情": {
        "时间": "2023年07月26日12:00:02",
        "地点": "天津",
        "人物观点": {
            "陈敏尔(天津市委书记)": "天津正全面贯彻党的二十大精神，认真落实习近平总书记在深入推进京津冀协同发展座谈会上的重要讲话精神，充分发挥区位、产业、科教人才、港口等优势，组织实施高质量发展“十项行动”，推动经济运行持续好转，努力实现质的有效提升和量的合理增长。希望中国大唐集团以此次签约为契机，与天津市深化能源保供合作，从合作存量中做大增量，积极在津布局科技创新、清洁能源、能源大数据、高端装备制造等新业务，共同推动京津冀协同发展取得更大成效。",
            "邹磊(中国大唐集团党组书记、董事长)": "中国大唐将自觉服务京津冀协同发展重大国家战略，坚定履行能源保供责任，积极推进绿电入津，加大在津投资布局力度，进一步拓展合作空间，助力天津绿色低碳发展。"
        },
        "合作领域": "新能源、智慧城市建设、供热、金融、物流等"
    }
}