{
    "主题": "“杜苏芮”残余环流引发极端强降雨",
    "元信息": {
        "关键词": "台风 杜苏芮 残余环流 强降雨 京津冀鲁豫晋 气象灾害 雨量 风险"
    },
    "详情": {
        "1. 台风“杜苏芮”情况": {
            "1.1 台风减弱": "2023-07-29 08:00，台风“杜苏芮”在安徽省安庆市宿松县境内减弱为热带低压",
            "1.2 停止编号": "2023-07-29 11:00，中央气象台停止对台风“杜苏芮”的编号"
        },
        "2. 极端强降雨情况": {
            "2.1 影响地区": "京津冀鲁豫晋",
            "2.2 持续时间": "2023-07-29 至 2023-08-01",
            "2.3 降雨量预测": {
                "2.3.1 北京、天津、河北、山东西部、河南北部、山西东部等地": "大暴雨，累计降雨量50至150毫米，局地200至450毫米，最大小时降雨量30至60毫米",
                "2.3.2 京津冀部分地区": "局地可达600毫米以上，最大小时降雨量可达80毫米以上"
            },
            "2.4 强降雨特点": "具有持续时间长、影响范围广、累计雨量大等特点",
            "2.5 气象风险": "致灾风险高，特别是中小河流超警戒或超保证水位，太行山沿山地区山洪和地质灾害风险高，城市内涝和农田渍涝风险较高",
            "2.6 人口和面积影响": "累计降雨量100毫米以上降雨面积将达22万平方公里，影响人口1.3亿人"
        },
        "3. 气象局应急响应": {
            "3.1 启动时间": "2023-07-29",
            "3.2 级别": "重大气象灾害（暴雨）一级应急响应"
        },
        "4. 提醒和防御措施": {
            "4.1 气象专家观点": {
                "4.1.1 观点1": "此次强降雨可能接近或超过2012年“7.21”和2016年7月18日至20日降雨过程，致灾风险高",
                "4.1.2 观点2": "公众需注意关注雨情、汛情变化，做好相关防御措施",
                "4.1.3 观点3": "不要前往地质灾害易发区，路遇积水不要贸然涉水，以保障自身安全"
            }
        }
    }
}