{
    "主题": "中国拟修改刑法，加大对行贿犯罪惩治力度",
    "元信息": {
        "关键词": "中国 行贿犯罪 刑法 修正案 惩治力度 腐败"
    },
    "详情": {
        "修正案内容": {
            "加大对行贿犯罪的惩治力度": "对多次行贿、向多人行贿，国家工作人员行贿等六类情形从重处罚。",
            "调整行贿罪的起刑点和刑罚档次": "与受贿罪相衔接。",
            "单位行贿案件处罚调整": "将单位行贿罪刑罚由原来最高判处五年有期徒刑的一档刑罚，修改为两档刑罚：“三年以下有期徒刑或者拘役，并处罚金”和“三年以上十年以下有期徒刑，并处罚金”。",
            "惩治民营企业内部人员腐败相关犯罪": "增加对民营企业内部人员腐败相关犯罪的条款，追究刑事责任。",
            "腐败问题治理": "体现了中国党和国家对治理腐败问题的坚定决心，需要全社会的共同参与和共同监督。"
        },
        "人物观点": {
            "卢其龙CN070(责任编辑)": "这次修正案草案的提出是我国对腐败现象零容忍的表现，体现了我们党和国家对治理腐败问题的坚定决心。腐败是侵蚀社会根基的毒瘤，我们必须以更加坚决的态度和更加有力的措施予以打击。只有我们每一个公民都时刻保持清醒的头脑，不被腐败所侵蚀，才能让我们的社会更加公平、正义和美好。"
        }
    }
}