{
  "主题": "华为植树活动",
  "元信息": {
    "关键词": "华为 开发者大会2023 鸿蒙林 鸿蒙生态 伙伴"
},
  "详情": {
    "活动时间": "2023年8月6日",
    "活动地点": "东莞松山湖",
    "参与人数": "100多位",
    "活动内容": "华为携手合作伙伴代表共植“鸿蒙林”，共赴“植此青绿、荫翳可期”的鸿蒙之约。",
    "参与人员": {
      "华为终端云服务总裁朱勇刚": "独木不成林。我们希望能够和所有的合作伙伴一起共同灌溉，共同施肥，让这片林向下扎到根，向上捅破天；让我们的鸿蒙生态，立足于中国这片沃土，从松山湖这个宝地出发，真正走向全球，成为一个全球的生态。",
      "华为终端全球生态发展与运营部总裁戢仁贵": "鸿蒙生态已经是当下最具创新势能、最具发展潜力、最具商业前景的生态体系。独行快，众行远。鸿蒙世界里没有篱笆，只有共同灌溉。就像一片充满了创造力和想象力的沃土，HarmonyOS让汇聚到这里的开发者、生态伙伴、消费者，能早投入、早收获。未来，华为将持续专注聚合模式，深耕平台黑土地，携手伙伴做大生态蛋糕，共同让鸿蒙生态立足中国，走向世界，拥抱一个万物互联，富有无穷可能的未来。"
    },
    "凤凰木象征": "鸿蒙生态的蓬勃生命力，是生态建设的关键起点。",
    "鸿蒙生态发展情况": "搭载鸿蒙生态的设备数量已超7亿，HarmonyOS开发者人数超220万人。",
    "鸿飞计划": "华为面向鸿蒙生态伙伴发布了三年百亿投入的“鸿飞计划”，为伙伴提供技术支持、生态营销、商业合作等助力，共同繁荣鸿蒙新生态。",
    "未来展望": "华为将持续专注聚合模式，深耕平台黑土地，携手伙伴做大生态蛋糕，共同让鸿蒙生态立足中国，走向世界，拥抱一个万物互联，富有无穷可能的未来。"
  }
}