{
    "主题": "储备棉轮出政策及影响分析",
    "元信息": {
        "关键词": "储备棉轮出 抛储政策 增发进口配额 供需形势 棉价走势"
    },
    "详情": {
        "储备棉轮出政策": {
            "细则待发布": "中国储备棉管理有限公司将于7月下进行储备棉轮出，每日挂牌销售数量根据市场形势等安排，具体需要等待细则指引",
            "抛储数量待定": "公告未明确抛储数量是否超过传言的30万吨"
        },
        "增发进口配额政策": {
            "75万吨非国营滑准税进配额": "国家发改委宣布发放75万吨非国营滑准税进配额，不限定贸易方式"
        },
        "供需形势分析": {
            "全球棉花产量预估": "USDA报告上调23/24年度全球棉花产量预估2.6万吨至2543.9万吨",
            "全球棉花消费预估": "USDA报告下调23/24年度全球棉花消费预估12万吨至2535.4万吨",
            "期末库存预估": "USDA报告上调23/24年度全球棉花期末库存预估37.4万吨至2057.8万吨",
            "新疆棉花减产预期": "预计新疆棉花实播面积同比减少约8.5%，全疆棉花单产同比下降约6.7%，全疆棉花产量同比减少约14.7%，2023年新疆棉花产量可能在512万吨左右",
            "全球棉花供需形势": "美国和巴基斯坦的增产抵消中国和土耳其减产，消费的复苏则是全球性的，未来的变数在于面积、天气"
        },
        "棉价走势分析": {
            "新疆棉商业库存": "截至6月底新疆棉商业库存为182.56万吨，环比减少55.38万吨",
            "内地棉花商业库存": "截至6月底内地棉花商业库存为83.63万吨，环比减少6.71万吨",
            "郑棉牛市": "疆棉库存下降，旧作库存紧张叠加新作减产，郑棉牛市仍在",
            "纱厂生产状况": "纱厂开机高位下降，即期纺纱亏损较大，成品库存增加，原料库存略降",
            "布厂生产状况": "布厂开机高位下降，成品库存增加，原料库存低位略降",
            "季节性淡季加强": "季节性淡季加强，有一些负反馈出现",
            "棉价走势预测": "随着储备棉轮出政策落地，将缓解国内棉花库存偏紧预期，为下游纺织企业用棉提供保障。短期看，棉价上涨与下游纱布实际需求相背离，纱价跟涨乏力"
        },
        "人物观点": {
            "刘宇(投资咨询证号：Z0012343)": "储备棉轮出将缓解供应紧张预期，国内棉价涨势受阻"
        },
        "责任编辑": "赵思远"
    }
}