{
    "主题": "芯片减产逐渐见效！三星电子芯片部门亏损收窄料下半年需求反弹",
    "元信息": {
        "关键词": "芯片 减产 逐渐见效 三星电子 亏损 收窄 下半年 需求 反弹"
    },
    "详情": {
        "时间": "2023-07-2712:33",
        "地点": "",
        "情节": {
            "节点1": "三星电子和SK海力士预计全球芯片需求将逐步复苏",
            "节点2": "三星电子二季度业绩表现",
            "节点3": "下半年存储芯片市场预计将逐步走向稳定",
            "节点4": "三星电子季度收入同比下降22%",
            "节点5": "芯片部门报告当季亏损4.36万亿韩元",
            "节点6": "三星电子将继续在半导体领域进行投资",
            "节点7": "三星电子预计将于2024年底开始从德克萨斯州泰勒的工厂出货先进的4纳米芯片",
            "节点8": "三星电子还将在韩国平泽建立更多的生产基地",
            "节点9": "SK海力士表示AI将很快点燃期待已久的反弹",
            "节点10": "SK海力士计划进一步削减NAND的产量"
        },
        "人物观点": {
            "三星电子": "展望下半年，考虑到行业减产力度加大，（存储芯片）市场预计将逐步走向稳定",
            "SK海力士公司": "AI将很快点燃期待已久的反弹"
        }
    }
}