{
    "主题": "泰安高铁站普通座椅被按摩座椅替换问题",
    "元信息": {
        "关键词": "泰安高铁站 普通座椅 按摩座椅 替换问题 客流量"
    },
    "详情": {
        "问题描述": "泰安高铁站内普通座椅数量不足，被按摩座椅替换",
        "时间": "8月10日",
        "地点": "泰安高铁站",
        "具体情况": {
            "候车厅北区座椅": {
                "普通座椅数量": "60多个",
                "按摩座椅数量": "近500个",
                "按摩椅品牌": "摩享乐",
                "按摩套餐": {
                    "普通按摩椅": {
                        "最低价格": "8.8元/10分钟",
                        "最高价格": "15.8元/32分钟"
                    },
                    "高级按摩椅": {
                        "最低价格": "15元/15分钟",
                        "最高价格": "30元/45分钟"
                    }
                }
            },
            "候车厅南区座椅": {
                "普通按摩椅数量": "5排",
                "高级按摩椅数量": "1排"
            }
        },
        "人物观点": {
            "徐女士(青岛)": "普通座椅应该多于按摩座椅，挤占了公共候车资源",
            "旅客": "座椅上的按摩突出点不舒服，硌到背部疼痛"
        },
        "工作人员回复": "无法答复，需要向上级汇报"
    }
}