{
    "主题": "实干的重要性",
    "元信息": {
        "关键词": "习近平总书记 党的十八大 实干 笃行 亮眼成绩单 盐碱地 粮食安全 旱碱麦 丰收 历年之最 文化 版本 馆藏 生态环境 盐湖生态保护 修复工作 高质量发展 制造业 创新 科技创新 经济增长"
    },
    "详情": {
        "习近平总书记观点": "空谈误国，实干兴邦",
        "盐碱地资源": "我国可利用的盐碱地约5亿亩，对保障国家粮食安全具有重要战略意义",
        "旧城镇旱碱麦产量": "旧城镇9万多亩旱碱麦今年再获丰收，产量创历年之最",
        "中国国家版本馆": "中国国家版本馆真抓实干做好收藏主业，馆藏内容得到了很大程度的丰富",
        "盐湖生态保护与修复工作": "实干是做好盐湖生态保护与修复工作的必由之路",
        "制造业核心竞争力": "提升制造业核心竞争力，最根本的还是创新",
        "苏州华兴源创科技股份有限公司": "苏州华兴源创科技股份有限公司通过努力创新，苦干实干，不断强化企业科技创新主体地位",
        "2023年经济增长": "2023年开年以来，我国经济同比增长5.5%",
        "习近平总书记嘱托": "广大干部群众牢记习近平总书记嘱托，“实”字当头、“干”字为先，笃定信心，阔步前行"
    }
}