{
    "主题": "福建省发现国内面积最大的水松天然更新群落",
    "元信息":{
        "关键词": "福建 罗源县 西兰乡 甘厝村 水松 科研人员 保护拯救 活化石 保护野生植物资源"
},
    "详情": {
        "发现地点": "福建省罗源县西兰乡甘厝村",
        "时间": "2023-07-2214:53:35",
        "发现内容": "福建省林业科学研究院科研人员在罗源县西兰乡甘厝村调查时，发现了国内面积最大的水松天然更新群落。",
        "水松的特点": "水松是冰川世纪孑遗植物，是国家一级保护的极小种群野生植物，列入《世界自然保护联盟濒危物种》红色名录。",
        "水松分布情况": "根据国家林草局公布的第二次全国重点保护野生植物资源调查数据，我国水松有89个分布点，共912株，其中福建有573株。",
        "群落面积": "群落占地面积达81亩。",
        "群落成分": "共有水松植株76株及一定数量幼苗。",
        "水松群落的年龄": "87%的植株胸径都是小于20厘米，属于幼树，说明水松群落非常年轻，天然更新能力强，全国罕见。",
        "研究团队": {
            "福建省林业科学研究院水松课题负责人": "黄雍容",
            "观点原话": "他们去年开始深入调查全省水松资源，此次在甘厝村发现这片水松群落时，心情非常激动。更令科研人员惊喜的是一批幼苗的发现。在调查中，我们发现其他地方的野生种群多数出现老化衰退、天然更新不良、繁衍受阻。而这片群落87%的植株胸径都是小于20厘米，属于幼树，说明水松群落非常年轻，天然更新能力强，全国罕见。",
            "福建省林业科学研究院与罗源县林业局": "签订战略合作框架协议，准备在科技项目申报、水松林自然保护小区规划等方面加强合作。"
        },
        "水松保护": {
            "人为干扰因素": "令科研人员惊奇的是，这片水松生长在村道旁，人为干扰因素多，为何还能保护得这么好？",
            "甘厝村的保护措施": "甘厝村党支部书记、村委会主任甘盛良说，大家以前不知道这片水松是“国宝”，但一直将它们视为“吉祥树”“风水树”，祖祖辈辈加以保护。甘厝村先人迁徙到此地时，两棵水松母树就已存在，所以最早的自然村名叫“树兜”，在耕作、放牧时都会避开水松，为树木腾出成长空间。",
            "罗源县的保护措施": "罗源县政府于2016年对水松母树在内的全县253棵古树名木进行挂牌保护，并在西兰乡、飞竹乡、霍口乡等水松群落上游区域，持续实施林田湖草生态保护修复和水环境综合治理项目，为水松群落提供了优质水源和良好环境。",
            "水松林自然保护小区": "罗源县已设立水松林自然保护小区，加强保护管理。",
            "福建省林业科学研究院与罗源县林业局": "签订战略合作框架协议，准备在科技项目申报、水松林自然保护小区规划等方面加强合作。",
            "下一步计划": "罗源县将发挥水松群落资源优势，将物种保护与科普宣传相结合，打造生态文明建设教育基地。"
        }
    }
}