{
    "主题": "女子持无座车票霸座被行政拘留5日",
    "元信息":{
        "关键词": "无座车票 霸座 行政拘留"
    },
    "详情": {
        "事件时间": "2023-08-15",
        "地点": "广州",
        "人物观点": {
            "广州铁路公安局广州公安处": "打击突出违法犯罪，确保旅客群众安全满意出行"
        },
        "行动情况": {
            "行动时间": "8月11日至13日",
            "抓获违法犯罪人员数量": "75人",
            "抓获网上在逃人员数量": "1名",
            "行政拘留人数": "7人",
            "罚款人数": "54人",
            "警力出动情况": "1500余人次",
            "警车出动次数": "118次",
            "卡点数量": "51个",
            "检查车辆数量": "191台",
            "盘查人员次数": "1200余人次",
            "清查重点场所数量": "470余处",
            "巡查重点部位数量": "3000余处",
            "排查整改安全隐患数量": "76处",
            "组织群防群治人次": "1300余人次",
            "宣防点数量": "131个"
        },
        "行动内容": "加强显性用警，提升应急处置能力，对车站广场、进站区域、站周停车场、旅馆、网吧等人员聚集和治安复杂、阴暗角落开展巡查。督促、协同铁路部门围绕巡防、物防、技防风险隐患开展安全检查，推进站区治安清查、落客平台、消防基础防范等工作，排除各类安全隐患。"
    }
}