{
    "主题": "2023年前7月全国房地产市场基本情况",
    "元信息":{
        "关键词": "房地产 开发投资 住宅 销售额"
},
    "详情": {
        "时间": "2023-08-17",
        "房地产开发投资": {
            "数据": "67717亿元",
            "同比下降幅度": "8.5%",
            "住宅投资下降幅度": "7.6%"
        },
        "房屋竣工面积": {
            "增长幅度": "20.5%",
            "住宅竣工面积增长幅度": "20.8%"
        },
        "商品房销售额": {
            "数据": "70450亿元",
            "同比下降幅度": "1.5%",
            "住宅销售额增速": "0.7%"
        },
        "商品房销售面积": {
            "同比下降幅度": "6.5%",
            "住宅销售面积下降幅度": "4.3%"
        },
        "房地产市场观点": {
            "58安居客研究院院长张波": "7月底的政策信号对于市场热度回升起到一定作用，但8月依然需要可执行的政策在一二线城市全面落地，带动市场情绪回归理性。"
        },
        "待售面积": {
            "商品房待售面积增长幅度": "17.9%",
            "住宅待售面积增长幅度": "19.5%"
        },
        "商品房销售均价": {
            "数据": "10584元/平方米",
            "同比增速": "9.2%"
        }
    }
}