{
    "主题": "夫妻关系矛盾导致孩子遭虐待",
    "元信息":{
        "关键词": "夫妻关系 分手 孩子 虐待"
    },
    "详情": {
        "夫妻关系矛盾": {
            "继续纠缠": "有些人无法忍受夫妻关系矛盾，他们一定要继续纠缠对方。",
            "将孩子作为出气筒": "夫妻关系矛盾时，有些人会将无辜的孩子作为出气筒。"
        },
        "虐待事件发生经过": {
            "时间": "2023-08-17",
            "地点": "广东",
            "受害者": "朱女士的女儿",
            "伤害行为": "爸爸拿起一个装有重物的快递盒向女儿砸去",
            "伤害后果": "女儿被砸晕，眼睛受伤",
            "监控录像": "监控录像中显示爸爸砸向女儿的过程"
        },
        "孩子得到支持和保护": {
            "支持者": "朱女士的两个儿子",
            "行为": "两个儿子站出来保护姐姐，大声斥责爸爸，并关上门，紧紧抱住姐姐安慰她"
        },
        "朱女士的态度和打算": {
            "态度": "朱女士表示一定会争取回来抚养权",
            "隐情": "透露了她和前夫之间的隐情"
        }
    }
}