{
    "主题": "美国招聘速度放缓，缓解美联储下次会议的加息压力",
    "元信息": {
        "关键词": "美国 招聘速度 放缓 缓解 美联储 会议 加息 压力"
},
    "详情": {
        "时间": "2023-08-05 06:12:00",
        "地点": "美国",
        "内容": "美国雇主们在今年夏天放缓了招聘速度，进一步表明经济出现逐渐降温的迹象，这缓解了美联储在下次会议上加息的压力。最新数据显示，美国7月非农新增就业18.7万人，低于预期的19万人，若不考虑6月数据下修，7月创下2020年12月以来的最低纪录，连续第二个月低于预期；失业率降至3.5%，低于预期，处于50年低点；但工资继续稳步增长，平均时薪同比增长4.4%，高于预期的4.2%，环比增速维持在0.4%。工资继续强劲增长，低失业率使工人们仍然可以获得加薪。平均时薪已连续两年同比增长至少4%。美国汽车工人联合会本周寻求在下一份劳动合同中加薪40%。最近的工资涨幅与经济学家们认为的低且稳定的通胀水平并不一致。假设工人生产率温和增长，年工资增长率应在约3.5%的水平，才能让通胀率更接近美联储的目标。尽管工资数据还显示劳动力市场颇有热度，但如果近期通胀放缓的态势持续下去，叠加本周五的就业报告，美联储将能够在9月19日至20日的会议上维持利率不变。不过7月非农报告本身不太可能彻底锁定局面，美联储官员们将在9月会议前获得8月份的非农就业数据以及7月和8月的通胀数据。美联储官员们此前表示，他们预计就业增长将放缓，部分原因是他们在抗击通胀。",
        "人物观点": {
            "Nick Timiraos(华尔街日报记者)": "美国雇主们在今年夏天放缓了招聘速度，进一步表明经济出现逐渐降温的迹象，这缓解了美联储在下次会议上加息的压力。",
            "Nick Timiraos(华尔街日报记者)": "工资继续强劲增长，低失业率使工人们仍然可以获得加薪。",
            "Nick Timiraos(华尔街日报记者)": "最近的工资涨幅与经济学家们认为的低且稳定的通胀水平并不一致。",
            "Nick Timiraos(华尔街日报记者)": "如果近期通胀放缓的态势持续下去，叠加本周五的就业报告，美联储将能够在9月19日至20日的会议上维持利率不变。",
            "美联储官员们": "他们预计就业增长将放缓，部分原因是他们在抗击通胀。"
        }
    }
}