{
    "主题": "港交所上半年净利润创历史第二高",
    "元信息":{
        "关键词": "港交所 上半年 净利润 增长率 收入 其他收益 每股盈利 股息"
},
    "详情": {
        "时间": "2023-08-16 22:03:00",
        "地点": "香港",
        "收入及其他收益": "105.75亿港元",
        "收入及其他收益增长率": "18%",
        "净利润": "63.12亿港元",
        "净利润增加率": "31%",
        "基本每股盈利": "4.99港元",
        "每股中期股息": "4.5港元",
        "派息比率": "90%",
        "历史第二高": "今年上半年收入和其他收益及净利润为历史第二高，仅次于2021年上半年的纪录",
        "表现出色原因": "全球宏观经济不确定性和市场疲弱的背景下表现出色",
        "重大战略": "完善互联互通机制、推出港币人民币双柜台模式、开设港交所首个北美办事处",
        "香港现货市场成交量": "1155亿港元",
        "香港现货市场成交量减少率": "16%",
        "ETF市场成交金额": "117亿港元",
        "ETF市场成交金额增长率": "21%",
        "沪深港通表现": "持续强劲",
        "南向和北向成交量对比": "上升",
        "债券通北向通成交金额": "389亿元人民币",
        "债券通北向通成交金额增长率": "25%",
        "IPO市场表现": "全球新股市场表现疲软",
        "上市公司数量": "33家",
        "总集资额": "179亿港元",
        "上市申请处理中数量": "104宗",
        "新股市场复苏预测": "难以预测何时复苏，但当前加息周期预计接近尾声、内地推出不少刺激经济措施，应该可以带来更好的IPO市场前景",
        "市场对降低股票印花税呼声": "市场参与者期望任何降低交易成本的方法",
        "降低股票印花税决定因素": "政府如何平衡各方需求",
        "港交所保证市场发展方式": "寻求各种方式，做好基础设施，服务市场参与者",
        "下调股票印花税取决于": "香港特区政府决定"
    }
}