{
    "主题": "A股三大指数大幅低开",
    "元信息": {
        "关键词": "A股 三大指数 低开 深成指 创业板指 市场 回升 沪指 新低 早盘 探底 回落 券商板块 金融 中字头 人工智能概念 数据要素产业链 安妮股份 人民网 中原传媒 浙数文化 久远银海 证券行业 首创证券 国联证券 信达证券 太平洋 东吴证券 财达证券 旅游酒店板块 华天酒店 桂林旅游 张家界 君亭酒店 金陵饭店 西藏旅游 算力概念 鸿博股份 威士顿 首都在线 亚康股份 铭普光磁 SPD概念股 开开实业 塞力医疗 浙江震元 国科恒泰 中远海科 中钢国际 中国软件 中国外运 CRO板块 诺泰生物 阳光诺和 皓元医药 泓博医药 诚达药业 汽车整车板块 长安汽车 江淮汽车 比亚迪 长城汽车 房地产板块 特发服务 天房发展 荣盛发展 深振业A 个股云内动力 金龙鱼"
},
    "详情": {
        "大跌": {
            "下行空间": "并不大"
        },
        "市场观点": {
            "国君策略分析": "市场对于经济/地缘的看法并无太大分歧并已计价，悲观者筹码多数已出清，市场下行的空间并不大。另一方面，对政治局后政策发力的预期也已多数计价，市场需要新的增量政策。因此维持对大势的判断，股票指数横盘震荡。大跌之后下行有底，不必过虑。",
            "中银证券观点": "国内需求依旧处于磨底阶段，政策博弈进行时。往后看，地产暖风有望依旧，市场对于后续房企融资及高能级城市限购放松的政策预期正在发酵，货币政策也有望迎来进一步宽松，下半年国内基本面有望逐步迎来底部回温。政策密集释放期，市场下行风险有限，配置机会凸显。"
        },
        "时间": "2023-08-14 15:06:58",
        "细节": {
            "深成指": "跌超1%",
            "创业板指": "跌超1%",
            "沪指": "一度跌破前低创1月6日以来新低",
            "券商板块": "走高助力",
            "午后": {
                "大金融": "上行",
                "中字头": "板块纷纷上行"
            },
            "人工智能概念": {
                "上涨": "华是科技、英飞拓、竞业达等",
                "走高": "三大指数逐步反弹"
            },
            "重要板块综述数据要素产业链": {
                "上涨停": "安妮股份、人民网、中原传媒、浙数文化、久远银海等"
            },
            "证券行业": {
                "冲高回落": "首创证券一度涨停",
                "上涨": "国联证券、信达证券、太平洋、东吴证券、财达证券等"
            },
            "旅游酒店板块": {
                "异动": "华天酒店涨停",
                "上涨": "桂林旅游、张家界、君亭酒店、金陵饭店、西藏旅游等"
            },
            "算力概念": {
                "反弹": "鸿博股份涨停",
                "上涨": "威士顿、首都在线、亚康股份、铭普光磁等"
            },
            "SPD概念股": {
                "活跃": "开开实业涨停",
                "上涨": "塞力医疗触及涨停、浙江震元、国科恒泰小幅上涨"
            },
            "中字头板块": "午后发力，中远海科、中钢国际、中国软件、中国外运集体上扬",
            "CRO板块": {
                "低迷": "诺泰生物跌超6%",
                "跟随走弱": "阳光诺和、皓元医药、泓博医药、诚达药业等"
            },
            "汽车整车板块": {
                "走弱": "长安汽车、江淮汽车、比亚迪、长城汽车等"
            },
            "房地产板块": {
                "大跌": "特发服务跌近10%",
                "跌停": "天房发展、荣盛发展、深振业A"
            },
            "个股异动": "聚焦签署合计10.31亿元采购合同，云内动力3天2涨停",
            "上半年净利润同比减少逾50%": "金龙鱼跌超10%创上市以来新低"
        }
    }
}