{
    "主题": "诺基亚公布2023年二季度及半年报",
    "元信息": {
        "关键词": "诺基亚 2023年 二季度 半年报 销售净额 5G设备"
    },
    "详情": {
        "时间": "2023-07-20 13:40:27",
        "销售净额": "57.1亿欧元（当前约462.51亿元人民币）",
        "销售净额同比": "-3%",
        "营业利润": "4.74亿欧元（当前约38.39亿元人民币）",
        "营业利润预估": "4.827亿欧元",
        "营业利润同比": "-16%",
        "营业利润率": "8.3%",
        "营业利润率同比": "-130个基点",
        "净营收": "115.69亿欧元（当前约937.09亿元人民币）",
        "净营收同比": "3%",
        "净销售额同比": "持平（按固定汇率计算）",
        "净销售额同比增长": "27%（按固定汇率计算）",
        "销售前景": "232-246亿欧元",
        "可比运营利润区间预期": "11.5-13%",
        "人物观点": {
            "佩卡・伦德马克(诺基亚首席执行官)": "我们现在看到下半年的净销售额大致与上半年的网络基础设施和移动网络相当，Q4有一些连续改进的迹象"
        }
    }
}