{
    "主题": "博乐市青达拉街道：红领巾小课堂乐趣多",
    "元信息":{
        "关键词": "博乐市 青达拉街道 红领巾小课堂"
},
    "详情": {
        "红领巾小课堂": {
            "溢彩绘画小课堂": {
                "时间": "7月起",
                "地点": "红星路社区",
                "详情": "红星路社区特邀博乐市昱章学院的老师们，通过寓教于乐的方式，教授孩子们一些基本的绘画方法和要领，激发孩子们的创造力和想象力。"
            },
            "石榴籽家园小课堂": {
                "时间": "近一个月",
                "地点": "秀苑社区",
                "详情": "秀苑社区利用石榴籽家园开展了“红领巾小课堂”，除了暑假作业辅导外，还有刮画、立体书、串珠、超轻黏土等兴趣课，以及电路连接、垃圾分类等实践课和文艺课。"
            },
            "非遗传承小课堂": {
                "时间": "暑期",
                "地点": "仁和社区",
                "详情": "仁和社区开展组织辖区少年儿童学习手工簪花技艺，让孩子们学习簪花的基本操作与步骤，点亮孩子们对中国传统手工艺的向往。"
            },
            "消防知识小课堂": {
                "时间": "暑期",
                "地点": "八一路社区",
                "详情": "八一路社区组织辖区6~12岁小朋友开启了一段消防队观摩体验之旅，了解消防车辆的性能和装备器材，进行地震演练，提高小朋友们的消防安全意识。"
            },
            "军营体验小课堂": {
                "时间": "暑期",
                "地点": "秀苑社区、银河社区、书香社区、天山路社区",
                "详情": "秀苑社区、银河社区、书香社区、天山路社区组织辖区孩子们参观军营的团史馆，聆听先辈们的战斗故事，加深对国防的了解，传承红色基因。"
            }
        }
    }
}