{
    "主题": "2023年07月22日中央气象台发布暴雨蓝色预警",
    "元信息":{
        "关键词": "中央气象台 暴雨蓝色预警 内蒙古 辽宁 吉林 黑龙江 江西 湖南 强降水 强对流天气"
},
    "详情": {
        "预警时间": "2023年07月22日06时",
        "预警级别": "蓝色预警",
        "预计时间": "7月22日08时至23日08时",
        "受影响地区": "内蒙古东部、辽宁、吉林中西部、黑龙江南部、江西北部、湖南东北部等地的部分地区",
        "预计天气情况": "大到暴雨",
        "详细天气情况": {
            "内蒙古东南部": "大暴雨（100～180毫米）",
            "吉林西部": "大暴雨（100～180毫米）",
            "辽宁中西部": "大暴雨（100～180毫米）"
        },
        "强对流天气": "局地有雷暴大风等强对流天气",
        "防御指南": [
            "政府及相关部门按照职责做好防暴雨准备工作",
            "学校、幼儿园采取适当措施，保证学生和幼儿安全",
            "驾驶人员应当注意道路积水和交通阻塞，确保安全",
            "检查城市、农田、鱼塘排水系统，做好排涝准备"
        ],
        "责任编辑": "杨海琴"
    }
}