{
    "主题": "国家老年大学2023年秋季学期线下课程招生报名",
    "元信息": {
        "关键词": "国家老年大学 2023年秋季学期 线下课程 招生 报名"
    },
    "详情": {
        "线下课程报名": {
            "详情": "国家老年大学2023年秋季学期线下课程招生报名已启动",
            "时间": "2023年秋季",
            "地点": "魏公村校区",
            "状态": "火爆",
            "课程余位": "美妆、油画创作与鉴赏等课程还有余位"
        },
        "报名要求": {
            "详情": "年龄在50周岁以上、身心健康具备完全行为能力、能够坚持正常学习的学员均可报名"
        },
        "课程信息": {
            "学院数量": 6,
            "学院": ["书画学院", "人文学院", "生活学院", "健康学院", "表演学院", "音乐学院"],
            "课程数量": 58,
            "课程列表": [
                "彩墨画",
                "山水画",
                "旅游英语",
                "唐宋诗歌鉴赏",
                "朗诵",
                "钢琴",
                "识谱与合唱",
                "潮流手工与文化创意",
                "生活中的考古学",
                "插画",
                "美妆"
            ],
            "公益课程数量": 4,
            "公益课程": ["潮流手工与文化创意", "生活中的考古学"],
            "短训课程数量": 4,
            "短训课程": ["插画", "美妆"]
        },
        "开课时间": {
            "详情": "新学期开课时间为9月11日",
            "时间": "9月11日"
        },
        "授课地点": {
            "详情": "线下授课地点位于国家开放大学魏公村校区",
            "地点": "国家开放大学魏公村校区"
        }
    }
}