{
    "主题": "河南累计建成高标准农田8330万亩 有力支撑粮食产量",
    "元信息":{
        "关键词": "河南 累计 建成 高标准农田 8330万亩 粮食产量"
},
    "详情": {
        "建设高标准农田": {
            "概述": "河南目前已累计建成高标准农田8330万亩，支撑了全省粮食产量",
            "支撑粮食产量": "河南省把高标准农田建设作为保障国家粮食安全的一项重要政治任务，持之以恒地抓好推进落实，全省粮食产量连续6年持续稳定在1300亿斤以上",
            "示范区建设": "高标准农田示范区对于推动农业高质量发展具有引领和带动作用",
            "河南省高标准农田示范区建设实施方案": {
                "规划内容": "规划在黄淮海平原和南阳盆地的14个产粮大市，集中连片建设1500万亩亩均总投资超4000元的高标准农田示范区",
                "新增粮食产能": "推动全省粮食产能到2025年达到1400亿斤以上，为国家千亿斤粮食工程贡献了十分之一力量",
                "示范区进展": {
                    "去年建设情况": "去年已在中原农谷和周口农高区先期建设200万亩示范区，目前已完成工程建设",
                    "今年建设情况": "今年启动建设400万亩示范区，已开工31万亩、完成初步设计260万亩"
                }
            }
        },
        "融资和运营问题": {
            "融资问题": {
                "解决方案": "河南省总结基层经验，编制《“投融建运管”一体化推进操作导则》，探索运用市场化机制，通过项目建设主体、投融资主体和运营主体共同参与项目设计、筹融资、建设和运营管护，建立利益联结机制",
                "问题": "解决项目融资还款难、规模化运营程度低、工程设施管护缺位等问题"
            }
        },
        "标准化体系创建": {
            "工作内容": "启动实施全国高标准农田示范区标准化体系创建工作，制定发布了《高标准农田建设规范》等5个地方标准，初步形成高标准农田示范区建设的“河南标准”"
        }
    }
}