{
    "主题": "中国香港选手张家朗拿下男子花剑个人赛冠军，中国选手邵雅琦斩获女子佩剑个人赛金牌",
    "元信息":{
        "关键词": "成都大运会 男子花剑个人赛 女子佩剑个人赛 中国香港选手 张家朗 中国选手 邵雅琦 决赛"
    },
    "详情": {
        "时间": "2023-08-05 09:12:00",
        "地点": "成都",
        "男子花剑个人赛决赛": {
            "参赛选手": ["中国香港选手张家朗", "法国选手卢瓦泽尔"],
            "比赛结果": "张家朗以15：12的成绩夺冠",
            "人物观点": {
                "张家朗(中国香港选手)": "这是自己第一次也是最后一次参加大运会，希望和队友打好团体赛"
            }
        },
        "女子佩剑个人赛决赛": {
            "参赛选手": ["中国选手邵雅琦", "韩国选手崔知英"],
            "比赛结果": "邵雅琦以15：10的成绩夺冠",
            "人物观点": {
                "邵雅琦(中国选手)": "这块金牌弥补了我在亚锦赛和世锦赛中的遗憾，证明我可以赢，可以站上最高的领奖台"
            }
        }
    }
}