{
    "主题": "苏家屯区供暖工作质量保障",
    "元信息":{
        "关键词": "供暖 冬病夏治 三修 供暖企业 管网改造 保温度 煤炭储备"
},
    "详情": {
        "抢先抓早赶进度": {
            "时间": "4月初",
            "内容": "全区立即组织5家供暖企业开展三修工作，今年“三修”计划投资7973万元，现已完成6131万元，完成率76.9%，9.5公里老旧管网改造工程全面完成，确保8月底前完成全部“三修”工作。"
        },
        "多措并举提热度": {
            "内容": "通过立杠移位保障供暖稳定，今年苏家屯区在供暖管网改造过程中，将原有在居民屋内的立杠更改到楼梯间，并用保温棉包裹，提升温度的同时方便缩短应急抢修时间。通过拆联改造工程保障供暖质量，今年将富民小区、晟海阳光小区供暖管网并入金山热电供暖管网，切实提升居民供暖质量。同时，督促供暖企业提前做好煤炭储备工作，今年全区供暖企业计划储煤53万吨，目前，已储备煤炭34.8万吨，完成率65.7%。"
        },
        "精细安排保温度": {
            "内容": "今年结合全区老旧小区改造工程，在主管网改造的同时，对20年以上楼龄的小区供热管网进行更换，改造总长达13.9公里，同时通过增加外墙的保温，楼道立杠包裹，直接提升11092户居民的供暖效果，居民家中温度实际可以提升3℃～5℃，从根本上解决群众的供暖需求。"
        },
        "人物观点": {
            "张晓宁(沈阳日报/沈报全媒体记者)": "苏家屯区在供暖工作中，抢先抓早、多措并举，精细安排，确保供暖质量，解决居民的供暖需求。"
        }
    }
}