{
    "主题": "新闻发布会：《鲲鹏击浪》《迷墙》等作品亮相",
    "元信息":{
        "关键词": "新闻发布会 电影节 紫禁城之夜 《鲲鹏击浪》 《迷墙》 《天工之城》 《恰同学少年》 《红领巾》"
},
    "详情": {
        "时间": "2023-08-13 下午",
        "地点": "北京",
        "项目": {
            "电视剧": [
                "《鲲鹏击浪》",
                "《迷墙》",
                "《天工之城》"
            ],
            "电影": [
                "《恰同学少年》",
                "《红领巾》"
            ]
        },
        "人物观点": {
            "叶大鹰(导演)": "《红领巾》是红色三部曲终章，是庆祝新中国成立75周年，少先队成立75周年的献礼之作，自己将会尽最大能力再拍一部不同凡响的浪漫主义红色电影。",
            "郑晓龙(导演)": "该剧讲述的不是王侯将相、才子佳人的故事，而是当时社会底层工匠群体用智慧与努力，来建设紫禁城的故事。",
            "马继红(编剧)": "《鲲鹏击浪》创作于2019年，历经四年四易其稿。剧集拍摄期间遇到最大的挑战，便是来自男女一号主角的选角工作。剧组通过各种渠道审阅了6000份以上的演员资料，参加试戏的演员有千余人。",
            "余耕(编剧)": "剧本打磨前后历时两年多时间。"
        }
    }
}