{
    "主题": "泰国推广软实力",
    "元信息":{
        "关键词": "泰国 政府 软实力 美食 电影 时尚 泰拳 节日 旅游 收入"
},
    "详情": {
        "泰国政府推广软实力": {},
        "推广美食": {},
        "推广电影": {},
        "推广时尚": {},
        "推广泰拳": {},
        "推广节日": {},
        "泰国米其林指南": {},
        "东北地区美食": {},
        "2023年泰国旅游年": {},
        "泰国旅游相关收入目标": {},
        "泰国旅游局局长观点": {},
        "中国游客是重要客源": {},
        "泰拳是泰国政府力推的重点项目": {},
        "泰拳特点": {},
        "泰拳可作竞技比赛和表演": {},
        "泰拳为泰国带来收入的观点": {},
        "泰拳武术家观点": {},
        "泰拳学校": {},
        "2023惊艳泰拳节": {},
        "泰国外交部推广泰拳的社交媒体账号": {}
    }
}