{
  "主题": "品中国节唱诗词歌 汉语桥线上文化交流活动",
  "元信息": {
    "关键词": "中国节唱诗词歌 汉语桥线上文化交流活动"
},
  "详情": {
    "活动时间": "11月3日",
    "活动地点": "江苏省苏州市",
    "活动主办方": "中国人民对外友好协会和江苏省人民政府",
    "活动主题": "共建绿色城市 共享民生福祉",
    "友好省州和友好城市关系建立时间": "自1979年起",
    "友好省州和友好城市关系数目": "284对",
    "友好省州和友好城市的作用": "是深化中美人民友谊、实现互利共赢的重要载体",
    "习近平观点": {
      "习近平": "中美关系的基础在民间，力量源泉在人民友好。",
      "习近平": "中美友城大会是中美地方交流的重要机制，为推动中美友城发展、深化友城合作发挥了积极作用。",
      "习近平": "希望与会各方继续做中美地方交流的桥梁，助力两国省州、城市跨越浩瀚的太平洋，共同为推动中美关系健康稳定发展、增进两国人民福祉发挥更大作用。"
    },
    "胡志扬观点": {
      "胡志扬": "对江西财经大学始终坚持开放办学、加强国际合作给予充分肯定。",
      "胡志扬": "希望同学们能通过“品中国节唱诗词歌”汉语桥这个文化交流平台，深度感受中国传统文化的独特魅力，真正走进中国、爱上中国。",
      "胡志扬": "同时，诚挚欢迎同学们来中国、来江西学习、工作、旅游和交流。"
    },
    "刘小丽观点": {
      "刘小丽": "推进线上文化交流是学校加强国际中文教育的重要载体。",
      "刘小丽": "承办汉语桥活动已成为学校开展对外交流的品牌活动。",
      "刘小丽": "希望同学们积极参与，感受中国魅力，更好地了解中国，走进中国。"
    },
    "黄琼英观点": {
      "黄琼英": "中华文化博大精深，源远流长，吸引了世界各地汉语学习者。",
      "黄琼英": "越南文化和中国文化特别是传统节日有很多相似之处。",
      "黄琼英": "本次项目的主题充满了吸引力，活动的开展对学生们来说，更是一次非常宝贵、也是非常难忘的体验。"
    },
    "活动开幕仪式": {
      "书法表演": "由江西财经大学艺术学院罗时武教授进行",
      "乐器演奏": "由江西财经大学艺术学院宋韵佳、雷敏老师带来",
      "学员故事分享": "来自越南阮必成大学、仰光师范大学和江西财经大学的3位学员分享了自己与汉语结缘的故事",
      "诗词朗诵": "来自巴基斯坦和俄罗斯的留学生朗诵古诗",
      "活动特色": "通过讲、唱结合的方式，为来自世界各地的学员带来品读中国节日的诗乐之旅"
    },
    "江西财经大学线上课程": {
      "品牌名称": "语言文化线上课程",
      "依托平台": "教育部中外语言交流合作中心“汉语桥”线上交流项目和中文联盟平台",
      "已开展活动期数": "五期",
      "获得结业证书人数": "692名",
      "获得“优秀营员”称号人数": "241名"
    }
  }
}