{
    "主题": "马斯克与扎克伯格“八角笼约架”将在X平台直播",
    "元信息":{
        "关键词": "马斯克 扎克伯格 八角笼约架 直播"
  },
    "详情": {
        "时间": "2023年08月06日18:36",
        "地点": "X平台",
        "人物观点": {
            "马斯克(未知机构)": "这是一种文明的战斗形式。男人热爱战斗。",
            "马斯克(未知机构)": "扎克伯格与马斯克之战将在X上直播。所有收益将捐给退伍军人慈善机构。",
            "马斯克(未知机构)": "一整天都在举重，为格斗做准备。",
            "马斯克(未知机构)": "没有时间锻炼，所以就把举重带到了工作中。",
            "马斯克(未知机构)": "拉斯维加斯八角笼。",
            "扎克伯格(Meta首席执行官)": "地址发我。"
        },
        "其他细节": [
            "马斯克与Meta首席执行官扎克伯格之间的“八角笼约架”将在X平台直播",
            "马斯克宣布战斗收益将捐给退伍军人慈善机构",
            "马斯克准备和扎克伯格进行一场“笼中格斗”",
            "马斯克将举重为格斗做准备",
            "马斯克把举重带到了工作中",
            "马斯克表示男人热爱战斗",
            "Meta公司计划推出一个与推特竞争的平台“Threads”",
            "马斯克连续发推对Meta进行攻击",
            "马斯克和扎克伯格达成“约架”"
        ]
    }
}