{
    "主题": "辽宁省全面加强和改进新时代儿童青少年近视防控工作专项行动计划(2023—2025年)",
    "元信息":{
        "关键词": "辽宁省 教育厅 近视防控 小学 初中 高中 眼保健操 中考 健康环境 预警监测 体育锻炼 公共体育设施 视力健康干预"
},
    "详情": {
        "时间": "23-08-11 06:17",
        "发布单位": "辽宁省教育厅",
        "摘要": "辽宁省教育厅等多部门联合印发《辽宁省全面加强和改进新时代儿童青少年近视防控工作专项行动计划(2023—2025年)》，明确防控重点任务和保障措施。",
        "防控目标": "通过三年努力实现全省小学近视率年均下降1%、初中年均下降2%、高中年均下降1.2%的防控目标。",
        "眼保健操措施": "落实每天上下午各1次眼保健操的护眼措施，将眼保健操纳入中考体育与健康教育实践操作考试内容，考核结果计入中考总成绩。",
        "近视防控预警监测机制": "建立健全近视防控预警监测机制，中小学校、幼儿园配备近视防控基础设施设备，开展春秋季学期中小学生视力健康监测，把裸眼视力、屈光度等主要信息检测结果记入儿童青少年视力健康电子档案，通过数据平台实时追踪学生眼健康状况及影响因素，对视力发生异常的中小学生及时采取干预措施，控制近视发生发展。",
        "四项措施": "巩固“双减”成果、加强体育锻炼、强化用眼健康、改善用眼环境",
        "控制统一考试次数": "严格控制义务教育阶段学校统一考试次数",
        "使用符合用眼卫生要求的教科书、试卷等学习用品": "使用符合用眼卫生要求的教科书、试卷等学习用品",
        "开齐开足上好学校体育课程，保证每天校内1小时体育活动时间": "开齐开足上好学校体育课程，保证每天校内1小时体育活动时间",
        "推动公共体育设施免费或低收费开放": "持续推动各类公共体育设施向儿童青少年免费或低收费开放",
        "推动近视防控关口前移": "科学开展近视防控干预措施，推动近视防控关口前移，开展0—6岁儿童眼保健和视力检查工作",
        "家庭宣传教育": "面向家长开展有针对性的宣传教育，提升家庭近视防控知识和意识，自觉减少电子产品使用，改变家长“重医轻防”的观念",
        "学生矫正视力专属绿色通道": "开通学生矫正视力专属绿色通道，定期公布获得验光配镜服务认证名单",
        "公益服务": "鼓励公益基金、社会企业赋能眼健康公益事业，为贫困眼病学生开展免费检查、配镜资助、捐赠视力健康包等服务",
        "推动全省创建儿童青少年近视防控基地": "到2025年，全省累计创建省级儿童青少年近视防控改革试验区3个，儿童青少年近视防控试点县(市、区)30个，省级儿童青少年近视防控基地30个，儿童青少年近视防控示范学校500所，实现全省儿童青少年新发近视率明显下降，视力健康水平整体提升",
        "人物观点": {
            "沈报全媒体记者丁宁": "辽宁省教育厅要求各级教育行政部门和学校要将儿童青少年近视防控作为学校卫生与健康教育工作重要内容，提高学生视力健康知识知晓率和学生用眼行为改进率，降低近视发生率。"
        }
    }
}