{
    "主题": "2023“中华文化大乐园”泰国曼谷营开营",
    "元信息":{
        "关键词": "中华文化大乐园 甘肃省海外联谊会 泰国孔堤公学慈善会"
},
    "详情": {
        "时间": "2023年6月6日",
        "地点": "泰国曼谷",
        "主办单位": "中华海外联谊会",
        "承办单位": "甘肃省海外联谊会",
        "协办单位": "泰国孔堤公学慈善会",
        "捐款人": {
            "罗宗正博士": "在开营仪式上为孔堤公学捐款"
        },
        "出席人员": {
            "梁冰": "泰国华文民校协会主席",
            "罗宗正": "泰国华文教师公会主席",
            "陈贵荣": "孔堤公学慈善会主席",
            "部分学生家长": ""
        },
        "相关负责人": {
            "尹清敏": "甘肃省海外联谊会"
        },
        "开幕致辞": {
            "尹清敏": "希望通过此次活动促进中泰文化交流"
        },
        "罗宗正观点": "对中华海外联谊会等在泰国所做的华文教育推广工作给予高度评价。这种办营形式对提升华裔青少年学习中文兴趣、传承中华文化具有非常积极的作用。",
        "陈贵荣观点": "希望“中华文化大乐园”活动能通过寓教于乐的形式,让参营学生感受到中文与中华文化的魅力。",
        "活动内容": "精选12名优秀教师组成教学团队，开设国学、声乐、舞蹈、手工艺、武术、书法和绘画等课程。教学团队还展示了诗歌朗诵、民族舞蹈、中华武术及书画创作等才艺。",
        "活动时间": "为期10天"
    }
}