{
    "主题": "美国东南部暴风雨天气致百万用户停电",
    "元信息": {
        "关键词": "美国 东南部 暴风雨 天气 百万用户 停电"
    },
    "详情": {
        "时间": "2023-08-09",
        "地点": "美国东南部",
        "人物观点": {
            "美国人事管理办公室": "由于暴风雨天气来袭，包括白宫和美国国防部在内，美国首都华盛顿特区的美国政府办公室将提前关闭。",
            "美国国家气象局": "对华盛顿地区发布了第二高的4级（共5级）强风暴风险警告，称当地可能出现“破坏性的大风”、龙卷风和冰雹等极端天气。"
        },
        "细节": {
            "死亡人数": "2人",
            "受影响州数": "11个州",
            "停电用户数": "至少100万用户",
            "航班受影响数": "数千架次",
            "北卡罗来纳州停电用户数": "近25万用户",
            "宾夕法尼亚州停电用户数": "超过16万用户",
            "佐治亚州停电用户数": "超过10万用户",
            "马里兰州停电用户数": "超过10万用户",
            "南卡罗来纳州停电用户数": "超过6.7万用户",
            "航班取消数": "1500多个航班",
            "航班延误数": "至少7000个航班",
            "受影响机场": "纽约、费城、华盛顿、亚特兰大等城市的多个机场"
        }
    }
}