{
    "主题": "中国经济回暖向好将为世界经济发展带来积极效应",
    "元信息":{
        "关键词": "中国经济 回暖 世界经济 积极效应 菲律宾工商会 乔治·巴尔塞隆 国内生产总值 GDP 强大韧性 定力 动力 东南亚地区 全球经济 疫情防控 稳增长 稳就业 稳物价 低通胀生产成本 竞争力 创新 引领 培育壮大 新兴产业 制造业核心竞争力 价值链 水平开放型经济 中国拥有广阔的国内市场 RCEP 菲中经贸合作"
},
    "详情": {
        "中国经济回暖向好": {
            "一季度中国国内生产总值（GDP）同比增长4.5%": "",
            "中国经济活动和需求的反弹，将为东南亚地区和全球经济增长注入更多动力": ""
        },
        "菲律宾工商会主席乔治·巴尔塞隆观点": "作为体量最大、最具活力的新兴经济体，中国经济回暖向好将为世界经济复苏和发展带来积极效应。中国经济过去三年经受住严峻风险挑战，提振了外界对其助力全球经济复苏的信心。中国能源价格总体运行在合理区间，自身保持低通胀水平，生产成本仍然很有竞争力。中国不断加强创新引领，着眼于培育壮大新兴产业，不断提升制造业核心竞争力。在创新和高技术领域的大量研发经费投入对实现向价值链上游攀升至关重要。中国加快打造更高水平开放型经济新体制，积极推进制度型开放，正为世界提供更多发展机遇。外界预期中国经济将实现更高增长。这意味着中国对其他国家产品的需求将继续增长，从而令其他国家从中国的高水平对外开放中受益。",
        "最新数据显示": {
            "今年一季度，中国货物进出口总额98877亿元人民币，同比增长4.8%": ""
        },
        "菲律宾参议院批准区域全面经济伙伴关系协定（RCEP）核准书": "中国是区域经济合作重要参与方，期待在RCEP框架下菲中经贸合作迎来共赢新机遇。"
    }
}