{
    "主题": "2023年世界母乳喂养周活动",
    "元信息": {
        "关键词": "世界母乳喂养周 母乳喂养优惠活动"
    },
    "详情": {
        "一、活动主题": "助力职场家庭,促进母乳喂养",
        "二、活动时间": "2023年8月1日至7日",
        "三、活动目标": "进一步做好母乳喂养宣传教育,加强母乳喂养咨询指导,改善母乳喂养支持环境,持续推进《母乳喂养促进行动计划(2021—2025年)》落实",
        "四、活动内容": [
            {
                "标题": "创新母乳喂养宣传教育",
                "详情": "各地要聚焦活动主题,充分利用传统媒体和新媒体,采用多种形式,全方位、立体式开展母乳喂养宣传教育,普及母乳喂养的重要意义,传播母乳喂养理念、知识和技能,在全社会营造关心、支持母乳喂养的良好氛围"
            },
            {
                "标题": "加强母乳喂养咨询指导",
                "详情": "支持产后母婴同室、重视产后访视、产后42天健康检查等,强化孕期、产时和产后母乳喂养咨询指导,针对高危儿、早产儿、患病儿童家庭有针对性的进行母乳喂养咨询指导"
            },
            {
                "标题": "改善母乳喂养支持环境",
                "详情": "持续推动构建政府主导、部门协作、全社会参与母乳喂养,持续提升母乳喂养水平。公共场所和用人单位加强母婴设施建设,提高母婴设施配置率,改善喂养环境"
            }
        ],
        "五、母乳喂养的重要性": "母乳独特的营养成分、酶、激素、直接免疫、免疫调节、抗炎、抗氧化和生长因子,发挥协同保护作用,为婴儿健康带来免疫保护,为婴儿抵御常见疾病侵袭筑起一道强大的防线。母乳喂养有利于宝宝体格生长和智力发育,不仅可以增强孩子免疫力,降低腹泻、呼吸道感染等疾病风险,还有助于预防成年时期心脏病、高血压、2型糖尿病、肥胖等慢性病的发生",
        "人物观点": {
            "竞秀区妇幼保健院": "始终坚持和大力宣传母乳喂养"
        },
        "活动优惠": [
            {
                "标题": "乳腺检查免费",
                "详情": "活动期乳腺检查均免费(原乳腺触诊检查5元,红外线乳腺检查32元)"
            },
            {
                "标题": "治疗费用优惠",
                "详情": "乳腺检查存在问题(积乳、少乳、急慢性乳腺炎、乳腺增生)治疗费用享受8折优惠政策"
            }
        ],
        "活动时间": "2023年8月1日至7日",
        "活动地点": "竞秀区妇幼保健院",
        "科室位置": "门诊二楼西侧",
        "联系邮箱": "jxqfybjy@163.com",
        "医院地址": "保定市竞秀区建民街69号",
        "微信号": "bdsjxqfybjy"
    }
}