{
    "主题": "央视新闻报道：武警北京总队成功救援受困乘客",
    "元信息":{
        "关键词": "央视新闻 武警 北京总队 救援 受困乘客 先头救援力量 食品 衣物 药品 物资 落坡岭站 断水 断电 断信号 通信 联络 渠道 接驳列车"
  },
    "详情": {
        "救援行动": {
            "先头救援力量行动过程": "8月1日，总台记者跟随武警北京总队的先头救援力量，经过四个小时的长途跋涉，徒步12公里，挺进K396次列车受困的落坡岭站。",
            "给受困乘客和周边村民发放物资": "给受困的乘客和周边村民发放食品、衣物、药品等物资。",
            "现场情况": "现场仍存在断水断电断信号的情况。",
            "通信畅通联络渠道": "先头救援力量的成功挺进，为后方通信畅通了联络渠道，助力接下来的救援工作顺利开展。",
            "增援救援力量": "该总队持续增援救援力量前往受困地区。",
            "护送乘客转移": "运送物资的同时，护送乘客平安转移。",
            "第一批乘客转移": "8月2日凌晨2时许，第一批328名受困乘客在武警官兵的护送下，开始有序转移，并于6时许成功转移至斜河涧站。",
            "全部乘客转移": "目前所有乘客已乘坐接驳列车前往北京丰台站。",
            "旅客情况": "首批旅客年龄大多在20岁到40岁之间。"
        },
        "列车被困情况": {
            "列车被迫停车": "7月30日，K396次列车行驶至北京门头沟落坡岭站附近被迫停车。",
            "乘客滞留": "乘客滞留，引发关注。",
            "女乘务员的发言": "K396次列车车厢中一名女乘务员哽咽安抚旅客的发言在网上引发关注。她再三叮嘱乘客“领取物资千万不要拥挤，哪怕吃不上，免费的饭一会儿就好。我是个女人，也是别人家的孩子，我就是穿了这身衣服，我得对得起大家！”"
        },
        "相关时间": {
            "先头救援力量行动时间": "8月1日",
            "第一批乘客转移时间": "8月2日凌晨2时许",
            "全部乘客转移时间": "目前"
        },
        "相关地点": {
            "落坡岭站": "K396次列车被困的地点",
            "斜河涧站": "第一批乘客转移至的地点",
            "北京丰台站": "所有乘客前往的地点",
            "门头沟落坡岭站": "K396次列车被迫停车的地点"
        },
        "人物观点": {
            "女乘务员(未知机构/单位和头衔)": "领取物资千万不要拥挤，哪怕吃不上，免费的饭一会儿就好。我是个女人，也是别人家的孩子，我就是穿了这身衣服，我得对得起大家！"
        },
        "参考来源": {
            "央视新闻": "http://www.cctv.com",
            "观察者网": "http://www.guancha.cn"
        },
        "编辑": "刘丹",
        "举报/反馈": ""
    }
}