{
    "主题": "成都第31届世界大学生夏季运动会开幕式火炬点燃细节揭秘",
    "元信息":{
        "关键词": "成都世界大学生夏季运动会 开幕式 火炬点燃 陈维亚 航天员 叶光富"
  },
    "详情": {
        "时间": "2019/06/28 01:41:00",
        "地点": "成都",
        "人物观点": {
            "陈维亚(成都大运会总导演)": "本届世界大学生夏季运动会是第31届大运会，为什么不选31名火炬手点火呢？这是一个想法，当时提出来大家就觉得很好。在点火仪式中大家也看到了，前所未有选择了31位优秀的各界大学生代表共同点燃本届大运会的圣火，这也是大运会有史以来点火参与火炬手最多的一次。",
            "陈维亚(成都大运会总导演)": "大家也注意到，中间最主要的第一棒是成都籍的航天员叶光富。为什么选用航天员？他也是优秀大学生，同时他是成都籍的航天员，在他的家乡成都举办大运会，恰好他去年刚刚到太空回来，我们觉得请他来点燃圣火，作为第一个主火炬手再合适不过。我们说他就是离太阳最近的人，他采集了太阳的光芒火焰点燃了本次大运会的主火炬，他体现了青年人追求科技的态度，也代表了成都老百姓点燃火炬。"
        }
    }
}