{
    "主题": "2023年台湾地区领导人选举候选人侯友宜参访台中基层",
    "元信息": {
        "关键词": "2023年 台湾地区领导人选举 候选人 侯友宜 参访 台中 基层"
    },
    "详情": {
        "时间": "2023-08-11",
        "地点": "台中",
        "人物观点": {
            "侯友宜(中国国民党2024台湾地区领导人选举候选人、新北市长)": "这次选举是选择和平与战争的关键时刻，民进党再执政，两岸一定兵凶战危。执政不分颜色，然而这几年的民主不是人民作主，而是民进党做主。之前的im.B诈骗案，政客与商人勾结、诈骗，三年里，诈骗案件从6万件成长到13万件，根本原因是没有从源头管理。这几年薪水没涨，但通货膨胀导致物价高涨，他在南部市场长大，爸爸是猪肉摊商，所以他知道最辛苦的就是这些人，一定给他们照顾、关怀。他之前去日本参访时，大家最关心台海危机。他这一代很幸福，没遇过战争，但是面对现在紧张的两岸关系，民进党当局不是避战，而是延长兵役、提升防务预算。两岸要交流、对话，虽然制度不同，但可以和平相处，他希望下一代、下下一代的子孙要进入职场，远离战场。民进党“台独”党纲不改，若再次当选，两岸一定兵凶战危，且这几年光电、高端弊案都没有解决，“再让民进党做下去，台湾就烂光了。”"
        },
        "活动": [
            {
                "时间": "上午",
                "内容": "到企业参访、拜庙"
            },
            {
                "时间": "下午",
                "内容": "举行首场“庙口开讲”，现场约200位民众情绪沸腾，“冻蒜”声不断"
            }
        ]
    }
}