{
    "主题": "洪都拉斯与中国开始自由贸易协定谈判",
    "元信息":{
        "关键词": "洪都拉斯 中国 自由贸易协定 谈判 虾 香蕉 甜瓜 雪茄 牛肉 咖啡 一带一路 世贸组织 中国国际进口博览会"
},
    "详情": {
        "时间地点": {
            "启动仪式": "7月7日 在洪首都特古西加尔巴",
            "中洪经贸混委会首次会议": "7月7日",
            "中方代表团抵达洪都拉斯": "7月6日",
            "中国国际进口博览会": "11月 在上海举行"
        },
        "参与人物": {
            "塞拉托(洪都拉斯经济发展部长)": "自贸协定谈判标志着洪都拉斯与中国关系发展的“新里程碑”",
            "王受文(中国商务部国际贸易谈判代表兼副部长)": "希望协定涵盖货物和服务贸易，还包括双边投资",
            "雷纳(洪都拉斯外长)": "通过会议正式启动自由贸易协定谈判"
        },
        "内容": [
            "洪都拉斯和中国于7月7日在洪首都特古西加尔巴开始了自由贸易协定的第一轮谈判",
            "塞拉托和王受文出席了在特古西加尔巴举行的启动仪式，雷纳也出席了仪式",
            "洪都拉斯计划向中国出口的产品包括虾、香蕉、甜瓜、雪茄和牛肉等，咖啡将是首批进入中国市场的产品之一",
            "中方希望这份协定不仅涵盖货物和服务贸易，还包括双边投资",
            "塞拉托和王受文还共同主持召开中洪经贸混委会首次会议，讨论议题包括“一带一路”倡议、在世贸组织框架下开展合作，以及洪都拉斯参加中国国际进口博览会等",
            "中方代表团于7月6日抵达洪都拉斯",
            "洪都拉斯和中国将在特古西加尔巴举行一系列会议，以加强双边合作",
            "通过这些会议，洪中双方将正式启动自由贸易协定谈判",
            "洪都拉斯与中国于今年3月正式建立外交关系，6月，洪都拉斯总统卡斯特罗对中国进行国事访问期间，双方签署了投资、贸易、电信、科技创新等领域的一系列合作协议"
        ]
    }
}