{
    "主题": "夏日送清凉！浦东新区杨高公交“爱心接力站”已对外开放",
    "元信息":{
        "关键词": "浦东新区 杨高公交 爱心接力站 清凉 休息 游客 书籍 服务 设施"
    },
    "详情": {
        "时间": "2023-07-26 14:45:00",
        "地点": "陆家嘴公交枢纽站",
        "人物观点": {
            "保洁员(陆家嘴公交枢纽站)": "这里除了可以吹空调，休息休息，还可以吃饭，看书，“除了像我们这些工作人员，有时也会有游客进来休息、看书。”",
            "85路调度员牛佳妍": "“爱心接力站”的人最多，不少户外工作者在这里吃饭。"
        },
        "详情": {
            "介绍": "作为“爱心接力站”，为户外工作者及市民游客们送上了夏日里的一丝清凉。“杨高公交陆家嘴’爱心接力站’是在站点现有条件的基础上充分整合升级而成的，除公交驾驶员、调度员外，站点也为往来的送餐员、快递员、环卫工等群体提供服务，让户外劳动者吃饭有桌椅、喝水有去处、天热能乘凉、累了能休息、轻伤能处理，让他们在烈日下也有避暑的好去处。”",
            "书架": "相较于其他地方的“爱心接力站”，这里还有一整面书架，摆放着各种书籍，并起名为“渔书阅读室”，让人们在休息的同时，还可以安静地看书。",
            "游客服务": "陆家嘴公交枢纽站也是游客聚集地，“爱心接力站”也为有需求的游客提供服务。",
            "服务设施": "公交站点的爱心接力站虽小，却“五脏俱全”，内部除了配备有热水、直饮水设备、微波炉、桌椅、空调、冰箱、应急药箱等基础服务设施外，有条件的站点还配备了空气净化器、躺椅、母婴角和阅览室，为周边的市民乘客提供便利。",
            "户外工作者的好去处": "户外工作者爱心驿站的投用，让不少户外工作者有了“歇脚地”和“加油站”。杨高公交表示，将充分运用站场资源，做好“爱心接力站”的设备维护工作，真正为户外劳动者提供温暖又清凉的休息港湾。"
        }
    }
}