{
    "主题": "海军第44批护航编队访问缅甸",
    "元信息":{
        "关键词": "海军 第44批 护航 缅甸 仰光 中国驻缅甸大使陈海 海军船坞基地司令佐温少将 华人华侨"
},
    "详情": {
        "时间": "11月27日",
        "地点": "缅甸仰光",
        "人物观点": {
            "陈海(中国驻缅甸大使)": "中缅友谊万古长青"
        },
        "描述": "海军第44批护航编队抵达缅甸仰光进行为期4天的友好访问。中国驻缅甸大使陈海携使馆工作人员、缅海军船坞基地司令佐温少将携官兵代表以及约500名华人华侨到码头迎接。海军第44批护航编队由中国海军淄博舰、荆州舰组成，悬挂“中缅友谊万古长青”等横幅，由缅海军“德彬瑞梯”号护卫舰引导靠上仰光迪拉瓦码头。编队官兵身着洁白的军装在甲板上分区列队，精神抖擞欢迎人群挥舞着中缅两国国旗。陈海大使在淄博舰舰长、政委的陪同下检阅了淄博舰仪仗队并与编队指挥员进行了座谈交流。期间，编队指挥员将拜会缅军地高层领导慰问当地小学师生，编队官兵将与缅海军官兵进行专业交流、文体竞技以及相互参观军事设施等活动。淄博舰、荆州舰将举行舰艇开放并举办甲板招待会。",
        "图片": ["官兵整齐列队，向码头欢迎人群挥手致意", "码头欢迎人群挥舞五星红旗，热烈欢迎海军官兵", "码头欢迎人群挥舞五星红旗排队参观舰艇", "欢迎人群登舰参观，并合影留念", "华人华侨在舰艇前合影留念"]
    }
}