{
    "主题": "外卖小哥拿到高温补贴",
    "元信息": {
        "关键词": "外卖小哥 高温补贴 北京平谷 劳动者权利保障"
    },
    "详情": {
        "背景": {
            "内容": "北京市平谷区检察院开展新就业形态领域农民工讨薪和根治欠薪专项活动",
            "人物观点": {
                "黄魁(北京市平谷区检察院第四检察部副主任)": "应该督促加大欠薪问题查处力度,形成‘检察+行政’治理欠薪合力。"
            }
        },
        "发现": {
            "内容": "平谷区检察院发现两家外卖平台配送站点存在涉薪劳动纠纷支持起诉线索210条",
            "人物观点": {
                "杨媛媛(该院检察官)": "两家公司均未向外卖骑手足额发放今年夏季的高温津贴。",
                "黄魁(北京市平谷区检察院第四检察部副主任)": "依法让劳动者获取应得劳动报酬、享受国家补贴政策,不仅关系到个人,更关系民生民利,关乎社会的幸福安定。"
            }
        },
        "办案过程": {
            "内容": "办案检察官调取了两家公司的相关证据材料，确认劳动者与用人单位之间存在劳动关系",
            "人物观点": {
                "杨媛媛(该院检察官)": "平台站点与部分外卖配送员之间以签订合作协议、承包协议的方式代替签订劳动合同,有意规避了二者之间的劳动关系。如何认定这类合作协议、承包协议的性质,成为办案伊始的一大难题。"
            }
        },
        "解决方式": {
            "内容": "检察官与平台配送站点负责人沟通，阐释法律依据及政策，讲明检察机关的立场，解答外卖配送员的法律政策，介绍支持起诉职能，达成和解",
            "人物观点": {
                "黄魁(北京市平谷区检察院第四检察部副主任)": "该院将继续对准新就业形态劳动者权利保障中的问题,深入调研,积极作为、主动担当,帮助更多的劳动者拿起法律武器维护自身合法权益。"
            }
        }
    }
}