{
    "主题": "福建师范大学协和学院校友会召开第二届理事会换届大会",
    "元信息":{
        "关键词": "福建师范大学 协和学院 校友会 理事会 换届大会"
},
    "详情": {
        "时间": "12月7日",
        "地点": "福建师范大学协和学院",
        "人物观点": {
            "黎胜禄(福建师范大学校友会)": "长期以来协和学院校友会在增强校友归属感、提升校友文化品牌、助推学院事业发展等方面做出积极贡献。",
            "杨林香(协和学院当选会长)": "校友工作是学院一项基础性、长期性、战略性的工作。今后，她将与理事会全体成员为校友们搭建好三个平台：一是运行有力、联系紧密的交流平台；二是共谋发展、共同进步的合作平台；三是高雅健康、其乐融融的文化平台，让母校成为校友发展的坚强后盾，让校友成为学院建设的有力支撑。",
            "陈林男(学院常务副书记)": "校友永远是母校最宝贵的资源和财富，是推动母校事业发展最可信赖的力量。他期待，在新一届理事会的带领下，广大校友能够继续高度关注并积极参与学院的改革与发展，与母校携手并创“高水平、有特色、省内一流、全国知名的独立学院”建设新局面，在中国式现代化福建篇章中书写更加优异的“协和答卷”。"
        },
        "会议内容": [
            "听取并审议通过了校友会第一届理事会工作报告、学院校友会会徽标识和《第二届理事会选举办法（草案）》",
            "选举产生了第二届理事会机构成员",
            "黎胜禄副部长和院领导为第二届理事会成员颁发聘书",
            "杨林香院长作为当选会长讲话",
            "全体与会人员与广大校友们一同前往创和园为“校友之家”揭牌",
            "杨林香院长对广大校友助力学院20周年华诞表示衷心的感谢，希望校友们常回家看看，继续为母校的发展建言献策"
        ]
    }
}