{
    "主题": "贵阳甲秀楼景区工作人员拒绝游客避雨事件",
    "元信息": {
        "关键词": "贵阳甲秀楼景区 游客 避雨 工作人员 旅游业"
    },
    "详情": {
        "事件经过": {
            "游客遭遇大雨": "7月29日，贵阳甲秀楼景区附近下起大雨，网传游客欲进场躲雨，随行还有老人孩子，全身淋湿。",
            "工作人员拒绝游客进入景区避雨": "工作人员以马上下班清场为由，拒绝游客进景区门内躲雨。",
            "游客质疑工作人员做法": "游客质疑工作人员不关心游客遭遇大雨，问他们下班了游客怎么办，工作人员回答不知道游客怎么办。"
        },
        "网友观点": {
            "一方认为景区服务不人性化": "有人称景区格局太小，服务不人性化。",
            "另一方认为工作人员有权按时下班": "对底层打工人而言，到点下班没问题。如果这样，上级会让无偿加班的，凭什么你出去玩，就要牺牲另一个人的下班时间呢？",
            "网友提出的解决方案": "有网友建议景区可以谈谈价格，让工作人员加班几分钟来补偿，解决游客避雨的问题。"
        },
        "负面影响": "景区工作人员拒绝游客避雨的行为伤害了游客的心，违背了当地的旅游形象定位，产生了负面影响。",
        "旅游法规定": "旅游法规定，旅游者在遇到危险时有权请求旅游经营者、当地政府和相关机构进行救助，包括避雨。",
        "旅游行业预测": "中国旅游研究院预测，今年暑期国内旅游人数将达18.54亿人次，国内旅游收入将达1.2万亿元。"
    }
}