{
    "主题": "先锋艺术电影展",
    "元信息":{
        "关键词": "先锋艺术电影展 重庆大学 四川师范大学 电影展 影视问题"
},
    "详情": {
        "时间": "2023年12月9日",
        "地点": "四川师范大学",
        "活动内容": "第五届先锋艺术电影展线下主体活动于2023年12月9日至12月14日举行，展映包括剧情片、纪录片、动画片、实验影片等多元形式类型影片，同期将开展多场学术论坛与研讨会，共同探讨当下的影视问题与未来发展。",
        "历届情况": "先锋艺术电影展起始于2018年，至今成功举办四届。",
        "重要人物": {
            "陈佑松(四川师范大学影视与传媒学院院长)": "陈佑松在开幕式上发言",
            "米家山(国家一级导演、重庆大学美视电影学院特聘教授)": "米家山在开幕式上发言",
            "范蓓(重庆大学美视电影学院常务副院长)": "范蓓在开幕式上发言",
            "李冠一(美视电影学院先锋电影制片厂负责人)": "李冠一在开幕式上发言"
        },
        "主办单位": "重庆市电影局、重庆南岸区委宣传部、重庆大学党委宣传部、重大(重庆)美视电影学院管理有限公司、重庆大学美视电影学院、重庆电影集团、四川师范大学影视与传媒学院等单位",
        "支持单位": "教育部思想政治工作创新发展中心(重庆大学)、重庆市电影家协会、重庆市制片行业协会",
        "展映单元": [
            {
                "时间": "12月9日-12日",
                "地点": "先锋艺术电影院、美视电影学院",
                "单元名称": "无界Boundless特展单元"
            },
            {
                "时间": "12月9日-12日",
                "地点": "先锋艺术电影院、美视电影学院",
                "单元名称": "主竞赛作品展映单元"
            },
            {
                "时间": "12月9日-12日",
                "地点": "先锋艺术电影院、美视电影学院",
                "单元名称": "致敬主席展映单元"
            },
            {
                "时间": "12月9日-12日",
                "地点": "先锋艺术电影院、美视电影学院",
                "单元名称": "川渝力量展映单元"
            },
            {
                "时间": "12月9日-12日",
                "地点": "先锋艺术电影院、美视电影学院",
                "单元名称": "闭幕影片展映"
            }
        ],
        "学术研讨会": [
            {
                "主题": "人工智能与中国电影工业的发展",
                "时间": "12月13日8:30-12:00",
                "地点": "美视电影学院小剧场"
            },
            {
                "主题": "中国影视产业现状与影视教育的未来",
                "时间": "12月13日14:00-18:00",
                "地点": "美视电影学院小剧场"
            },
            {
                "主题": "影视创作教学与影展作为一种教育模式",
                "时间": "12月14日8:30-12:00",
                "地点": "美视电影学院小剧场"
            },
            {
                "主题": "影展策划的实现与中国电影产业发展",
                "时间": "12月13日19:30-22:00",
                "地点": "美视电影学院8楼艺术沙龙"
            }
        ],
        "闭幕红毯&荣誉盛典": {
            "内容": "红毯仪式+闭幕颁奖典礼",
            "地点": "重庆大学B区科学会堂",
            "时间": "12月14日14:30"
        }
    }
}