{
    "主题": "2018黄龙庙会民俗文化活动",
    "元信息": {
        "关键词": "黄龙庙会 民俗文化活动 黄龙地区"
    },
    "详情": {
        "时间": "2018-07-27",
        "地点": "黄龙后寺广场",
        "活动内容": [
            "舞龙表演",
            "山歌《雪山人》",
            "舞蹈《安多草原》",
            "琵琶弹唱《十二将》",
            "秧歌《人逢喜事精神爽》",
            "广场舞《泉水叮咚响》",
            "民族服饰展示"
        ],
        "活动亮点": [
            "黄龙庙会是古老的传统民俗文化活动",
            "融合了博大精深的民俗文化的精粹",
            "为助力振兴旅游,彰显黄龙独特的资源优势和古老的文化魅力",
            "再现黄龙庙会传统民俗风情",
            "扩大旅游消费",
            "全面提升黄龙风景区品牌社会影响力",
            "拉动当地经济又快又好发展",
            "发挥促进作用",
            "实现社会效益、经济效益、生态效益和文化效益良好结合的目标"
        ],
        "人物观点": {
            "四川雅安游客": "黄龙景区的景色宜人,美不胜收。黄龙庙会的民俗文化节目丰富多彩,令人应接不暇,感觉不虚此行!"
        },
        "活动目标": [
            "挖掘黄龙丰富的文化内涵",
            "弘扬和展示悠久的民俗文化、民俗风情",
            "加强交流",
            "增进友谊",
            "营造景区良好的文化氛围",
            "树立黄龙多元文化旅游品牌形象",
            "提升黄龙景区知名度",
            "增强吸引力",
            "促进文旅相融",
            "助推全域旅游发展"
        ],
        "地理信息": {
            "黄龙地理位置": "四川省阿坝藏族羌族自治州松潘县境域",
            "与其他地区相连": [
                "北界九寨沟县",
                "西靠红原县",
                "西北与若尔盖县连接",
                "东依平武县",
                "东南与北川县接壤"
            ]
        },
        "旅游资源": [
            "黄龙风景区：被誉为“人间瑶池”、“圣地仙境”",
            "岷山主峰雪宝鼎：终年积雪不化，成为当地神山崇拜体系的核心",
            "各民族村寨、大小庙会等文化元素"
        ],
        "民族文化": "汉风、藏韵、羌情、回俗在这里汇聚,各民族独具魅力的服饰特点、饮食习惯、建筑方式、歌舞娱乐等在长期的民族杂居中得到了促进与融合,相互影响,相互渗透"
    }
}